keymint/__init__.py
keymint/_version.py
keymint/types.py
keymint-2.0.0.dist-info/licenses/LICENSE
keymint-2.0.0.dist-info/METADATA
keymint-2.0.0.dist-info/WHEEL
keymint-2.0.0.dist-info/top_level.txt
keymint-2.0.0.dist-info/RECORD
