Metadata-Version: 2.4
Name: keymint
Version: 2.0.0
Summary: Official Python SDK for KeyMint license management with comprehensive API coverage.
Home-page: https://github.com/keymint-dev/keymint-python
Author: KeyMint
Author-email: admin@keymint.dev
Project-URL: Bug Reports, https://github.com/keymint-dev/keymint-python/issues
Project-URL: Source, https://github.com/keymint-dev/keymint-python
Project-URL: Documentation, https://docs.keymint.dev/sdks/python
Project-URL: Homepage, https://keymint.dev
Keywords: keymint license licensing api sdk drm software-licensing
Classifier: Development Status :: 5 - Production/Stable
Classifier: Intended Audience :: Developers
Classifier: Topic :: Software Development :: Libraries :: Python Modules
Classifier: Topic :: System :: Software Distribution
Classifier: License :: OSI Approved :: MIT License
Classifier: Programming Language :: Python :: 3
Classifier: Programming Language :: Python :: 3.6
Classifier: Programming Language :: Python :: 3.7
Classifier: Programming Language :: Python :: 3.8
Classifier: Programming Language :: Python :: 3.9
Classifier: Programming Language :: Python :: 3.10
Classifier: Programming Language :: Python :: 3.11
Classifier: Programming Language :: Python :: 3.12
Classifier: Operating System :: OS Independent
Requires-Python: >=3.6
License-File: LICENSE
Requires-Dist: requests>=2.25.0
Provides-Extra: dev
Requires-Dist: pytest>=6.0; extra == "dev"
Requires-Dist: pytest-cov; extra == "dev"
Requires-Dist: black; extra == "dev"
Requires-Dist: flake8; extra == "dev"
Dynamic: author
Dynamic: author-email
Dynamic: classifier
Dynamic: description
Dynamic: description-content-type
Dynamic: home-page
Dynamic: keywords
Dynamic: license-file
Dynamic: project-url
Dynamic: provides-extra
Dynamic: requires-dist
Dynamic: requires-python
Dynamic: summary
